llmatch/__init__.py
llmatch-2025.4.181303.dist-info/licenses/LICENSE
tests/__init__.py
llmatch-2025.4.181303.dist-info/METADATA
llmatch-2025.4.181303.dist-info/WHEEL
llmatch-2025.4.181303.dist-info/top_level.txt
llmatch-2025.4.181303.dist-info/RECORD
